cosmic_variance/__init__.py
cosmic_variance/cosmic_variance.py
cosmic_variance/quickcv/quickcv.py
cosmic_variance/quickcv/utils/__init__.py
cosmic_variance/quickcv/utils/dlin.py
cosmic_variance/quickcv/utils/intpk4.py
cosmic_variance/quickcv/utils/pofk.py
cosmic_variance/quickcv/utils/rz.py
cosmic_variance-0.1.6.dist-info/AUTHORS.rst
cosmic_variance-0.1.6.dist-info/LICENSE
cosmic_variance-0.1.6.dist-info/METADATA
cosmic_variance-0.1.6.dist-info/WHEEL
cosmic_variance-0.1.6.dist-info/top_level.txt
cosmic_variance-0.1.6.dist-info/RECORD
