Metadata-Version: 2.1
Name: cosmic-variance
Version: 0.1.6
Summary: Package to calculate cosmic variance in rectangular pencil-beam surveys
Home-page: https://github.com/astrockragh/cosmic_variance
Author: Christian Kragh Jespersen
Author-email: ckragh@princeton.edu
License: MIT license
Keywords: Cosmology,Galaxies,Statistics,Astrostatistics,Cosmic Variance
Platform: UNKNOWN
Classifier: Development Status :: 4 - Beta
Classifier: Intended Audience :: Developers
Classifier: License :: OSI Approved :: MIT License
Classifier: Natural Language :: English
Classifier: Programming Language :: Python :: 3
Classifier: Programming Language :: Python :: 3.6
Classifier: Programming Language :: Python :: 3.7
Classifier: Programming Language :: Python :: 3.8
Requires-Python: >=3.6
Requires-Dist: numpy (>=1.17.0)
Requires-Dist: scipy (>=1.2.0)
Requires-Dist: pandas (>=1.0.0)
